{
  " мин": "",
  "Бюджет": "",
  "Время": "Время",
  "Год производства": "Год производства",
  "Детектив": "Детектив",
  "Драма": "Драма",
  "Жанр": "",
  "Жанры": "",
  "Италия": "Италия",
  "Комедия": "Комедия",
  "Композитор": "",
  "Маркетинг": "",
  "Монтаж": "",
  "Мультфильм": "Мультфильм",
  "О фильме": "О фильме",
  "Оператор": "",
  "По дате выхода": "",
  "По количеству оценок": "",
  "По названию": "",
  "По порядку": "",
  "По рейтингу": "",
  "Поиск": "Поиск",
  "Продюсер": "",
  "Режиссера": "",
  "Россия": "Россия",
  "СССР": "СССР",
  "США": "США",
  "Сборы в США": "",
  "Сборы в мире": "Сборы в мире",
  "Сбросить": "Сбросить",
  "Слоган": "",
  "Сортировать": "",
  "Страна": "Страна",
  "Страны": "",
  "Сценарий": "",
  "Трейлер": "Трейлер",
  "Фантастика": "Фантастика",
  "Фильм не найден": "",
  "Фильмы не найдены": "Фильмы не найдены",
  "Франция": "Франция",
  "Художник": "",
  "детектив": "",
  "драма": "",
  "комедия": "",
  "мин": "мин",
  "мультфильм": "",
  "фантастика": ""
}
